03.方法字节码

栈帧（stack frame）  
栈帧是一种用于帮助虚拟机执行方法调用与方法执行的数据结构  
栈帧封装了方法的局部变量表、动态链接信息、方法的返回地址以及操作数栈等信息  

符号引用、直接引用  
有些符号引用是在类加载阶段或是第一次使用时就会转换为直接引用，这种转换叫做静态解析；另外一些符号引用则是在每次<font color=red>运行期</font>转换为直接引用，这种转换叫做动态链接，这体现为java的多态性  

字节码指令：  
1. invokeinterface: 调用接口中的方法，实际上是在运行期决定的，决定到底调用实现该接口的哪个对象的特定方法

解析阶段就可以确定的
>2. invokestatic: 调用静态方法
>3. invokespecial: 调用自己的私有方法、构造方法(<init>)以及父类的方法
4. invokevirtual: 调用虚方法，运行期动态查找的过程
5.  invokedynamic: 动态调用方法  


静态解析的4种情形：  
1. 静态方法
2. 父类方法
4. 构造方法
4. 私有方法（无法被重写）

*以上4类方法称作非虚方法，他们是在类加载阶段就可以将符号引用转换为直接以用*


###### 方法的静态分派  

方法重载示例代码：
```java
package com.faa.jvm;

public class MyTest5 {

    public void test(Grandpa grandpa) {
        System.out.println("grandpa");
    }

    public void test(Father father) {
        System.out.println("father");
    }

    public void test(Son son) {
        System.out.println("son");
    }

    public static void main(String[] args) {
        Grandpa g1 = new Father();
        Grandpa g2 = new Son();

        MyTest5 myTest5 = new MyTest5();

        myTest5.test(g1);
        myTest5.test(g2);
    }

}

class Grandpa {}

class Father extends Grandpa {}

class Son extends Father {}
```

执行结果：  
```
grandpa
grandpa
```

jclasslib查看方法符号表：  
```
 0 new #7 <com/faa/jvm/Father>
 3 dup
 4 invokespecial #8 <com/faa/jvm/Father.<init>>
 7 astore_1
 8 new #9 <com/faa/jvm/Son>
11 dup
12 invokespecial #10 <com/faa/jvm/Son.<init>>
15 astore_2
16 new #11 <com/faa/jvm/MyTest5>
19 dup
20 invokespecial #12 <com/faa/jvm/MyTest5.<init>>
23 astore_3
24 aload_3
25 aload_1
26 invokevirtual #13 <com/faa/jvm/MyTest5.test>
29 aload_3
30 aload_2
31 invokevirtual #13 <com/faa/jvm/MyTest5.test>
34 return

```

解析：  
Grandpa g1 = new Father();
g1的静态类型是Grandpa, 而g1的实际类型（真正指向的类型）是Father。
变量的静态类型是不会发生变化的，而变量的 的实际类型则是可以变化的（多态的一种体现），实际类型是在运行期才可以确定的  
这是<font color=red>方法重载</font>，是一种<font color=red>静态行为</font>，<font color=red>编译期</font>就可以完全确定。<font color=red>传递的参数类型取决于声明它的类型</font>。  

   

###### 方法的动态分派

方法重写示例代码：  
```java
package com.faa.jvm;

public class MyTest6 {

    public static void main(String[] args) {
        Fruit apple = new Apple();
        Fruit orange = new Orange();

        apple.test();
        orange.test();

        apple = new Orange();
        apple.test();
    }

}

class Fruit {
    public void test() {
        System.out.println("fruit");
    }
}

class Apple extends Fruit {
    @Override
    public void test() {
        System.out.println("apple");
    }
}

class Orange extends Fruit {
    @Override
    public void test() {
        System.out.println("orange");
    }
}
```

jclasslib查看符号表：  
```
 0 new #2 <com/faa/jvm/Apple>
 3 dup
 4 invokespecial #3 <com/faa/jvm/Apple.<init>>
 7 astore_1
 8 new #4 <com/faa/jvm/Orange>
11 dup
12 invokespecial #5 <com/faa/jvm/Orange.<init>>
15 astore_2
16 aload_1
17 invokevirtual #6 <com/faa/jvm/Fruit.test>
20 aload_2
21 invokevirtual #6 <com/faa/jvm/Fruit.test>
24 new #4 <com/faa/jvm/Orange>
27 dup
28 invokespecial #5 <com/faa/jvm/Orange.<init>>
31 astore_1
32 aload_1
33 invokevirtual #6 <com/faa/jvm/Fruit.test>
36 return

```

执行结果：  
```
apple
orange
orange
```

解析：   
方法的动态分派涉及到一个重要概念：方法接收者
比较方法重载(overload)与方法重写，可以得到结论：方法重载是静态的，是编译器行为；方法重写是动态的，是运行期行为


示例代码：  
```java
package com.faa.jvm;

import java.util.Date;

public class MyTest7 {

    public static void main(String[] args) {
        Animal animal = new Animal();
        Animal dog = new Dog();
        animal.test("hello");
        dog.test(new Date());
    }

}

class Animal {
    public void test(String str) {
        System.out.println("animal str");
    }

    public void test(Date date) {
        System.out.println("animal date");
    }
}

class Dog extends Animal {
    @Override
    public void test(String str) {
        System.out.println("dog str");
    }

    @Override
    public void test(Date date) {
        System.out.println("dog date");
    }
}
```
执行结果：  
```
animal str
dog date
```

解析：  
*虚方法表*
针对于方法调用动态分配的过程，虚拟机会在类的方法区建立一个虚方法表的数据结构(virtual method table, vtable), 针对于 invokeinterface指令来说，虚拟机会建立一个叫做接口方法表的数据结构(interface method table, itable)


示例伪代码：  
```
public class Parent {
    void test1
    void test2
}

public class Child extends Parent {
    void test1
    void test2
    void test3
}

Parent child = new Child();
child.test3();
```
结果：  
编译报错。Parent类中没有test3()。Parent child是静态解析



<font color=purple>new的作用</font>：  
1. 为对象开辟内存空间 
2. 调用构造函数
3. 返回对象在堆上的引用


<font color=purple>基于栈的指令集与基于寄存器的指令集之间的关系</font>：
1. jvm执行指令时所采取的方式是基于栈的指令集
2. 基于栈的指令集主要的操作有入栈和出栈两种
3. 基于栈的指令集的优势在于它可以在不同平台之间移植，而基于寄存器的指令集是与硬件架构 紧密关联的，无法做到可移植性
4. 基于栈的指令集的缺点在于完成相同的操作，指令数量通常要比基于寄存器的指令数量多；基于栈的指令集是在内存中完成操作的，
而基于寄存器的指令集是直接由cpu来执行的，它是在高速缓冲区中进行执行的，速度要快得多。虽然虚拟机可以采用一些优化手段，
但总体来说，基于栈的指令集的执行速度要慢一些


jvm执行栈指令集

示例代码：  
```java
public class MyTest8 {

    public int myCalculate() {
        int a = 1;
        int b = 2;
        int c = 3;
        int d = 4;

        int result = (a + b - c) * d;

        return result;
    }

}
```
jclasslib查看字节码：  
```
 0 iconst_1     //将1放到操作数栈的栈顶
 1 istore_1     //将操作数栈顶的值弹出，将局部变量表索引位置为1的值设为当前值
 2 iconst_2
 3 istore_2
 4 iconst_3
 5 istore_3
 6 iconst_4
 7 istore 4     //istore_n最多到3，所以此处没有下划线
 9 iload_1      //将局部变量表中索引为1的值压到栈顶
10 iload_2
11 iadd
12 iload_3
13 isub
14 iload 4
16 imul
17 istore 5
19 iload 5
21 ireturn
```


动态代理实现机制
P57-P58
















